mailmanfetch.py
mailman_fetch-0.1.2.dist-info/METADATA
mailman_fetch-0.1.2.dist-info/RECORD
mailman_fetch-0.1.2.dist-info/WHEEL
mailman_fetch-0.1.2.dist-info/entry_points.txt
mailman_fetch-0.1.2.dist-info/top_level.txt
